waylay/sdk/__init__.py
waylay/sdk/_version.py
waylay/sdk/client.py
waylay/sdk/exceptions.py
waylay/sdk/py.typed
waylay/sdk/api/__init__.py
waylay/sdk/api/_models.py
waylay/sdk/api/client.py
waylay/sdk/api/constants.py
waylay/sdk/api/exceptions.py
waylay/sdk/api/http.py
waylay/sdk/api/httpx_types.py
waylay/sdk/api/serialization.py
waylay/sdk/auth/__init__.py
waylay/sdk/auth/exceptions.py
waylay/sdk/auth/interactive.py
waylay/sdk/auth/model.py
waylay/sdk/auth/parse.py
waylay/sdk/auth/provider.py
waylay/sdk/config/__init__.py
waylay/sdk/config/client.py
waylay/sdk/config/model.py
waylay/sdk/plugin/__init__.py
waylay/sdk/plugin/base.py
waylay/sdk/plugin/client.py
waylay/sdk/plugin/loader.py
waylay/sdk/plugin/type_stubs.py
waylay/sdk/services/gateway.py
waylay_sdk_core-0.4.1.dist-info/licenses/LICENSE.txt
waylay_sdk_core-0.4.1.dist-info/METADATA
waylay_sdk_core-0.4.1.dist-info/WHEEL
waylay_sdk_core-0.4.1.dist-info/entry_points.txt
waylay_sdk_core-0.4.1.dist-info/top_level.txt
waylay_sdk_core-0.4.1.dist-info/RECORD
