Metadata-Version: 2.4
Name: waylay-sdk-core
Version: 0.4.1
Summary: Waylay Python SDK.
Author-email: Waylay <info@waylay.io>
License: ISC License (ISC)
Project-URL: Homepage, https://www.waylay.io/
Project-URL: Documentation, https://docs.waylay.io/#/
Project-URL: Repository, https://github.com/waylayio/waylay-sdk-py.git
Keywords: waylay,sdk
Requires-Python: >=3.9
License-File: LICENSE.txt
Requires-Dist: httpx
Requires-Dist: appdirs
Requires-Dist: pyjwt
Requires-Dist: python_dateutil
Requires-Dist: typing_extensions>=4.10.0
Requires-Dist: typeguard
Requires-Dist: jsonpath-ng
Requires-Dist: pydantic>=2.6.0
Requires-Dist: eval-type-backport>=0.3; python_version < "3.10"
Requires-Dist: waylay-beta==0.0.999
Provides-Extra: dev
Requires-Dist: pytest; extra == "dev"
Requires-Dist: pytest-cov; extra == "dev"
Requires-Dist: pytest-mock; extra == "dev"
Requires-Dist: pytest-httpx; extra == "dev"
Requires-Dist: pytest-asyncio; extra == "dev"
Requires-Dist: starlette; extra == "dev"
Requires-Dist: numpy; extra == "dev"
Requires-Dist: syrupy; extra == "dev"
Requires-Dist: ruff; extra == "dev"
Requires-Dist: mypy!=1.11.*; extra == "dev"
Requires-Dist: pyjwt; extra == "dev"
Requires-Dist: types-appdirs; extra == "dev"
Requires-Dist: types-python-dateutil; extra == "dev"
Requires-Dist: pre-commit; extra == "dev"
Requires-Dist: sse-starlette; extra == "dev"
Dynamic: license-file
